[
  {
    "id": "cmnlv88z20001f87sjf1i65f7",
    "orderNumber": "ORD-2026-0001",
    "customerId": "cmnd79sve000cf854b07akqcy",
    "shippingName": "John Smith",
    "shippingPhone": "9460056944",
    "shippingAddress": "N/A, Consolacion Road, Guinhalaran, Mambulac, Silay, Negros Occidental, 6116, Philippines",
    "shippingCity": "Silay",
    "shippingState": "Negros Occidental",
    "shippingZipCode": "6116",
    "shippingCountry": "Philippines",
    "shippingLatitude": 10.7861262,
    "shippingLongitude": 122.9743197,
    "billingName": null,
    "billingAddress": null,
    "billingCity": null,
    "billingState": null,
    "billingZipCode": null,
    "billingCountry": null,
    "status": "OUT_FOR_DELIVERY",
    "priority": "normal",
    "subtotal": 828,
    "tax": 66.24,
    "shippingCost": 0,
    "discount": 0,
    "totalAmount": 894.24,
    "paymentStatus": "pending",
    "paymentMethod": "COD",
    "warehouseId": "cmnd79svx000ef854zezvp9zj",
    "notes": null,
    "specialInstructions": null,
    "confirmedAt": "2026-04-05T14:37:45.466Z",
    "processedAt": "2026-04-05T14:37:45.466Z",
    "shippedAt": "2026-04-05T15:02:26.888Z",
    "deliveryDate": "2026-04-06T14:37:26.500Z",
    "deliveredAt": null,
    "cancelledAt": null,
    "createdAt": "2026-04-05T14:37:26.507Z",
    "updatedAt": "2026-04-05T15:02:26.905Z"
  },
  {
    "id": "cmnlvgdlk0005f87s7il3khch",
    "orderNumber": "ORD-2026-0002",
    "customerId": "cmnd79sve000cf854b07akqcy",
    "shippingName": "John Smith",
    "shippingPhone": "9460056944",
    "shippingAddress": "N/A, Langka Street, Guinhalaran, Mambulac, Silay, Negros Occidental, 6116, Philippines",
    "shippingCity": "Silay",
    "shippingState": "Negros Occidental",
    "shippingZipCode": "6116",
    "shippingCountry": "Philippines",
    "shippingLatitude": 10.78787156570303,
    "shippingLongitude": 122.9755274366811,
    "billingName": null,
    "billingAddress": null,
    "billingCity": null,
    "billingState": null,
    "billingZipCode": null,
    "billingCountry": null,
    "status": "OUT_FOR_DELIVERY",
    "priority": "normal",
    "subtotal": 621,
    "tax": 49.68,
    "shippingCost": 0,
    "discount": 0,
    "totalAmount": 670.68,
    "paymentStatus": "pending",
    "paymentMethod": "COD",
    "warehouseId": "cmnd79svx000ef854zezvp9zj",
    "notes": null,
    "specialInstructions": null,
    "confirmedAt": "2026-04-05T14:47:13.944Z",
    "processedAt": "2026-04-05T14:47:13.944Z",
    "shippedAt": "2026-04-05T15:02:26.888Z",
    "deliveryDate": "2026-04-06T14:43:45.749Z",
    "deliveredAt": null,
    "cancelledAt": null,
    "createdAt": "2026-04-05T14:43:45.752Z",
    "updatedAt": "2026-04-05T15:02:26.905Z"
  },
  {
    "id": "cmnlvgmns0009f87sam0b6i5m",
    "orderNumber": "ORD-2026-0003",
    "customerId": "cmnd79sve000cf854b07akqcy",
    "shippingName": "John Smith",
    "shippingPhone": "9460056944",
    "shippingAddress": "N/A, Langka Street, Guinhalaran, Mambulac, Silay, Negros Occidental, 6116, Philippines",
    "shippingCity": "Silay",
    "shippingState": "Negros Occidental",
    "shippingZipCode": "6116",
    "shippingCountry": "Philippines",
    "shippingLatitude": 10.78787156570303,
    "shippingLongitude": 122.9755274366811,
    "billingName": null,
    "billingAddress": null,
    "billingCity": null,
    "billingState": null,
    "billingZipCode": null,
    "billingCountry": null,
    "status": "OUT_FOR_DELIVERY",
    "priority": "normal",
    "subtotal": 1035,
    "tax": 82.8,
    "shippingCost": 0,
    "discount": 0,
    "totalAmount": 1117.8,
    "paymentStatus": "pending",
    "paymentMethod": "COD",
    "warehouseId": "cmnd79svx000ef854zezvp9zj",
    "notes": null,
    "specialInstructions": null,
    "confirmedAt": "2026-04-05T14:47:23.600Z",
    "processedAt": "2026-04-05T14:47:23.600Z",
    "shippedAt": "2026-04-05T15:02:26.888Z",
    "deliveryDate": "2026-04-06T14:43:57.492Z",
    "deliveredAt": null,
    "cancelledAt": null,
    "createdAt": "2026-04-05T14:43:57.496Z",
    "updatedAt": "2026-04-05T15:02:26.905Z"
  },
  {
    "id": "cmnlvha0l000df87s2tr92kq0",
    "orderNumber": "ORD-2026-0004",
    "customerId": "cmnd79sve000cf854b07akqcy",
    "shippingName": "John Smith",
    "shippingPhone": "9460056944",
    "shippingAddress": "N/A, Zulueta Street, Poblacion, Mambulac, Silay, Negros Occidental, 6116, Philippines",
    "shippingCity": "Silay",
    "shippingState": "Negros Occidental",
    "shippingZipCode": "6116",
    "shippingCountry": "Philippines",
    "shippingLatitude": 10.79892737393843,
    "shippingLongitude": 122.9754800848129,
    "billingName": null,
    "billingAddress": null,
    "billingCity": null,
    "billingState": null,
    "billingZipCode": null,
    "billingCountry": null,
    "status": "DELIVERED",
    "priority": "normal",
    "subtotal": 1035,
    "tax": 82.8,
    "shippingCost": 0,
    "discount": 0,
    "totalAmount": 1117.8,
    "paymentStatus": "pending",
    "paymentMethod": "COD",
    "warehouseId": "cmnd79svx000ef854zezvp9zj",
    "notes": null,
    "specialInstructions": null,
    "confirmedAt": "2026-04-05T14:47:26.102Z",
    "processedAt": "2026-04-05T14:47:26.102Z",
    "shippedAt": "2026-04-05T15:02:26.888Z",
    "deliveryDate": "2026-04-06T14:44:27.759Z",
    "deliveredAt": "2026-04-05T15:51:39.409Z",
    "cancelledAt": null,
    "createdAt": "2026-04-05T14:44:27.764Z",
    "updatedAt": "2026-04-05T15:51:39.422Z"
  },
  {
    "id": "cmnmmmpri0008f8d8i1ql2pnk",
    "orderNumber": "ORD-2026-0005",
    "customerId": "cmnd79sve000cf854b07akqcy",
    "shippingName": "John Smith",
    "shippingPhone": "9460056944",
    "shippingAddress": "N/A, Zulueta Street, Poblacion, Mambulac, Silay, Negros Occidental, 6116, Philippines",
    "shippingCity": "Silay",
    "shippingState": "Negros Occidental",
    "shippingZipCode": "6116",
    "shippingCountry": "Philippines",
    "shippingLatitude": 10.79892737393843,
    "shippingLongitude": 122.9754800848129,
    "billingName": null,
    "billingAddress": null,
    "billingCity": null,
    "billingState": null,
    "billingZipCode": null,
    "billingCountry": null,
    "status": "DELIVERED",
    "priority": "normal",
    "subtotal": 1035,
    "tax": 82.8,
    "shippingCost": 0,
    "discount": 0,
    "totalAmount": 1117.8,
    "paymentStatus": "pending",
    "paymentMethod": "COD",
    "warehouseId": "cmnd79svx000ef854zezvp9zj",
    "notes": null,
    "specialInstructions": null,
    "confirmedAt": "2026-04-06T03:24:45.276Z",
    "processedAt": "2026-04-06T03:24:45.276Z",
    "shippedAt": "2026-04-06T03:29:48.859Z",
    "deliveryDate": "2026-04-07T00:00:00.000Z",
    "deliveredAt": "2026-04-06T03:30:09.003Z",
    "cancelledAt": null,
    "createdAt": "2026-04-06T03:24:31.086Z",
    "updatedAt": "2026-04-06T03:30:09.020Z"
  },
  {
    "id": "cmnmmqofq000cf8d80pl8xpeb",
    "orderNumber": "ORD-2026-0006",
    "customerId": "cmnd79sve000cf854b07akqcy",
    "shippingName": "John Smith",
    "shippingPhone": "9460056944",
    "shippingAddress": "Burgos Street, Barangay I, Bugbog, Sibunag, Sibunag, Guimaras, 5048, Philippines",
    "shippingCity": "Sibunag",
    "shippingState": "Guimaras",
    "shippingZipCode": "5048",
    "shippingCountry": "Philippines",
    "shippingLatitude": 10.4977743,
    "shippingLongitude": 122.6628983,
    "billingName": null,
    "billingAddress": null,
    "billingCity": null,
    "billingState": null,
    "billingZipCode": null,
    "billingCountry": null,
    "status": "OUT_FOR_DELIVERY",
    "priority": "normal",
    "subtotal": 414,
    "tax": 33.12,
    "shippingCost": 0,
    "discount": 0,
    "totalAmount": 447.12,
    "paymentStatus": "pending",
    "paymentMethod": "COD",
    "warehouseId": "cmnd79svx000ef854zezvp9zj",
    "notes": null,
    "specialInstructions": null,
    "confirmedAt": "2026-04-06T03:28:22.187Z",
    "processedAt": "2026-04-06T03:28:22.187Z",
    "shippedAt": "2026-04-06T03:29:48.859Z",
    "deliveryDate": "2026-04-07T00:00:00.000Z",
    "deliveredAt": null,
    "cancelledAt": null,
    "createdAt": "2026-04-06T03:27:35.991Z",
    "updatedAt": "2026-04-06T03:29:48.921Z"
  },
  {
    "id": "cmnmmrc0x000gf8d8au9ws3zm",
    "orderNumber": "ORD-2026-0007",
    "customerId": "cmnd79sve000cf854b07akqcy",
    "shippingName": "John Smith",
    "shippingPhone": "9460056944",
    "shippingAddress": "Burgos Street, Guimaras Circumferential Road, Bugbog, Bugbog, Sibunag, Guimaras, 5048, Philippines",
    "shippingCity": "Sibunag",
    "shippingState": "Guimaras",
    "shippingZipCode": "5048",
    "shippingCountry": "Philippines",
    "shippingLatitude": 10.49786202558503,
    "shippingLongitude": 122.6653343818071,
    "billingName": null,
    "billingAddress": null,
    "billingCity": null,
    "billingState": null,
    "billingZipCode": null,
    "billingCountry": null,
    "status": "OUT_FOR_DELIVERY",
    "priority": "normal",
    "subtotal": 50,
    "tax": 4,
    "shippingCost": 0,
    "discount": 0,
    "totalAmount": 54,
    "paymentStatus": "pending",
    "paymentMethod": "COD",
    "warehouseId": "cmnd79svx000ef854zezvp9zj",
    "notes": null,
    "specialInstructions": null,
    "confirmedAt": "2026-04-06T03:28:23.971Z",
    "processedAt": "2026-04-06T03:28:23.971Z",
    "shippedAt": "2026-04-06T03:29:48.859Z",
    "deliveryDate": "2026-04-07T00:00:00.000Z",
    "deliveredAt": null,
    "cancelledAt": null,
    "createdAt": "2026-04-06T03:28:06.561Z",
    "updatedAt": "2026-04-06T03:29:48.921Z"
  }
]